odoo/addons/account_tax_legal_notes_translate/README.rst
odoo/addons/account_tax_legal_notes_translate/__init__.py
odoo/addons/account_tax_legal_notes_translate/__manifest__.py
odoo/addons/account_tax_legal_notes_translate/i18n/account_tax_legal_notes_translate.pot
odoo/addons/account_tax_legal_notes_translate/i18n/it.po
odoo/addons/account_tax_legal_notes_translate/models/__init__.py
odoo/addons/account_tax_legal_notes_translate/models/account_tax.py
odoo/addons/account_tax_legal_notes_translate/readme/CONTRIBUTORS.md
odoo/addons/account_tax_legal_notes_translate/readme/DESCRIPTION.md
odoo/addons/account_tax_legal_notes_translate/static/description/icon.png
odoo/addons/account_tax_legal_notes_translate/static/description/index.html
odoo_addon_account_tax_legal_notes_translate-18.0.1.0.1.1.dist-info/METADATA
odoo_addon_account_tax_legal_notes_translate-18.0.1.0.1.1.dist-info/WHEEL
odoo_addon_account_tax_legal_notes_translate-18.0.1.0.1.1.dist-info/top_level.txt
odoo_addon_account_tax_legal_notes_translate-18.0.1.0.1.1.dist-info/RECORD
