Metadata-Version: 2.1
Name: odoo-addon-account_tax_legal_notes_translate
Version: 18.0.1.0.1.1
Requires-Python: >=3.10
Requires-Dist: odoo==18.0.*
Summary: Agrega traducciones a las notas legales de los impuestos
Home-page: https://github.com/OCA/account-invoicing
License: AGPL-3
Author: Moduon, Odoo Community Association (OCA)
Author-email: support@odoo-community.org
Classifier: Programming Language :: Python
Classifier: Framework :: Odoo
Classifier: Framework :: Odoo :: 18.0
Classifier: License :: OSI Approved :: GNU Affero General Public License v3
